{"mc":{
	"warsp000_2a":{
		"frameRate":6,
		"frames":[
			{"res":"attack1_2_00020","x":-140,"y":-311},
			{"res":"attack1_2_00021","x":-132,"y":-312},
			{"res":"attack1_2_00022","x":-123,"y":-312},
			{"res":"attack1_2_00023","x":-128,"y":-311},
			{"res":"attack1_2_00024","x":-130,"y":-312},
			{"res":"attack1_2_00025","x":-128,"y":-313},
			{"res":"attack1_2_00026","x":-132,"y":-304},
			{"res":"attack1_2_00027","x":-151,"y":-305},
			{"res":"attack1_2_00028","x":-158,"y":-308},
			{"res":"attack1_2_00029","x":-169,"y":-312}

		]
}},
"res":{
	"attack1_2_00020":{"x":0,"y":0,"w":225,"h":328},
	"attack1_2_00021":{"x":225,"y":0,"w":220,"h":342},
	"attack1_2_00022":{"x":445,"y":0,"w":218,"h":337},
	"attack1_2_00023":{"x":663,"y":0,"w":225,"h":320},
	"attack1_2_00024":{"x":888,"y":0,"w":242,"h":317},
	"attack1_2_00025":{"x":1130,"y":0,"w":234,"h":314},
	"attack1_2_00026":{"x":1364,"y":0,"w":237,"h":298},
	"attack1_2_00027":{"x":1601,"y":0,"w":247,"h":312},
	"attack1_2_00028":{"x":1364,"y":312,"w":247,"h":315},
	"attack1_2_00029":{"x":1611,"y":312,"w":265,"h":318}

}}