{"mc":{"csjz_03":{"frameRate":12,"frames":[{"res":"JieZhi_0000","x":-96,"y":-116},{"res":"JieZhi_0001","x":-96,"y":-117},{"res":"JieZhi_0002","x":-96,"y":-117},{"res":"JieZhi_0003","x":-96,"y":-117},{"res":"JieZhi_0004","x":-96,"y":-115},{"res":"JieZhi_0005","x":-96,"y":-113},{"res":"JieZhi_0006","x":-96,"y":-112},{"res":"JieZhi_0007","x":-96,"y":-112},{"res":"JieZhi_0008","x":-96,"y":-114},{"res":"JieZhi_0009","x":-96,"y":-115}]}},"res":{"JieZhi_0000":{"x":0,"y":0,"w":183,"h":230},"JieZhi_0001":{"x":183,"y":0,"w":184,"h":231},"JieZhi_0002":{"x":367,"y":0,"w":184,"h":231},"JieZhi_0003":{"x":551,"y":0,"w":183,"h":231},"JieZhi_0004":{"x":734,"y":0,"w":183,"h":229},"JieZhi_0005":{"x":917,"y":0,"w":185,"h":227},"JieZhi_0006":{"x":1102,"y":0,"w":184,"h":226},"JieZhi_0007":{"x":1286,"y":0,"w":183,"h":226},"JieZhi_0008":{"x":1469,"y":0,"w":183,"h":228},"JieZhi_0009":{"x":1652,"y":0,"w":183,"h":229}}}