{"mc":{"weaponsoul_in_2_1":{"frameRate":10,"frames":[{"res":"101","x":-278,"y":-31},{"res":"102","x":-276,"y":-30},{"res":"103","x":-271,"y":-31},{"res":"104","x":-270,"y":-34},{"res":"105","x":-270,"y":-23},{"res":"106","x":-273,"y":-23},{"res":"107","x":-276,"y":-9},{"res":"108","x":-278,"y":-5}]}},"res":{"101":{"x":0,"y":0,"w":303,"h":242},"102":{"x":303,"y":0,"w":301,"h":248},"103":{"x":604,"y":0,"w":298,"h":238},"104":{"x":902,"y":0,"w":298,"h":239},"105":{"x":1200,"y":0,"w":298,"h":227},"106":{"x":1498,"y":0,"w":301,"h":225},"107":{"x":1498,"y":225,"w":303,"h":209},"108":{"x":604,"y":239,"w":305,"h":207}}}