{"mc":{
	"monster10069_4r":{
		"frameRate":12,
		"frames":[
			{"res":"176","x":-99,"y":-229},
			{"res":"177","x":-108,"y":-227},
			{"res":"178","x":-106,"y":-237},
			{"res":"179","x":-111,"y":-228},
			{"res":"180","x":-113,"y":-227},
			{"res":"181","x":-108,"y":-236}

		]
}},
"res":{
	"176":{"x":0,"y":0,"w":208,"h":270},
	"177":{"x":208,"y":0,"w":216,"h":243},
	"178":{"x":424,"y":0,"w":210,"h":246},
	"179":{"x":634,"y":0,"w":209,"h":265},
	"180":{"x":843,"y":0,"w":212,"h":241},
	"181":{"x":1055,"y":0,"w":213,"h":247}

}}