{"mc":{
	"monster20043_1r":{
		"frameRate":15,
		"frames":[
			{"res":"10012","x":-55,"y":-107},
			{"res":"10013","x":-57,"y":-107},
			{"res":"10014","x":-57,"y":-106},
			{"res":"10015","x":-60,"y":-105},
			{"res":"10016","x":-63,"y":-144},
			{"res":"10017","x":-62,"y":-165},
			{"res":"10018","x":-59,"y":-142},
			{"res":"10019","x":-53,"y":-105}

		]
}},
"res":{
	"10012":{"x":0,"y":0,"w":138,"h":117},
	"10013":{"x":138,"y":0,"w":125,"h":114},
	"10014":{"x":263,"y":0,"w":128,"h":102},
	"10015":{"x":391,"y":0,"w":144,"h":111},
	"10016":{"x":535,"y":0,"w":137,"h":158},
	"10017":{"x":672,"y":0,"w":119,"h":176},
	"10018":{"x":791,"y":0,"w":129,"h":153},
	"10019":{"x":920,"y":0,"w":133,"h":110}

}}