{"mc":{
	"monster10030_2r":{
		"frameRate":12,
		"frames":[
			{"res":"140","x":-98,"y":-89},
			{"res":"141","x":-96,"y":-91},
			{"res":"142","x":-96,"y":-93},
			{"res":"143","x":-99,"y":-87},
			{"res":"144","x":-102,"y":-85},
			{"res":"145","x":-101,"y":-83}

		]
}},
"res":{
	"140":{"x":0,"y":0,"w":181,"h":96},
	"141":{"x":181,"y":0,"w":181,"h":98},
	"142":{"x":362,"y":0,"w":183,"h":99},
	"143":{"x":545,"y":0,"w":188,"h":94},
	"144":{"x":733,"y":0,"w":193,"h":92},
	"145":{"x":926,"y":0,"w":186,"h":91}

}}