{"mc":{
	"monster84004_3d":{
		"frameRate":10,
		"frames":[
			{"res":"119","x":-145,"y":-263},
			{"res":"120","x":-162,"y":-262},
			{"res":"121","x":-158,"y":-265},
			{"res":"122","x":-154,"y":-269},
			{"res":"123","x":-148,"y":-270},
			{"res":"124","x":-147,"y":-267}

		]
}},
"res":{
	"119":{"x":0,"y":0,"w":262,"h":259},
	"120":{"x":262,"y":0,"w":380,"h":256},
	"121":{"x":642,"y":0,"w":374,"h":265},
	"122":{"x":1016,"y":0,"w":372,"h":265},
	"123":{"x":1388,"y":0,"w":366,"h":266},
	"124":{"x":262,"y":256,"w":350,"h":267}

}}