{"mc":{
	"monster10108_4r":{
		"frameRate":12,
		"frames":[
			{"res":"176","x":-161,"y":-285},
			{"res":"177","x":-160,"y":-288},
			{"res":"178","x":-158,"y":-290},
			{"res":"179","x":-160,"y":-293},
			{"res":"180","x":-162,"y":-292},
			{"res":"181","x":-164,"y":-289}

		]
}},
"res":{
	"176":{"x":0,"y":0,"w":269,"h":308},
	"177":{"x":269,"y":0,"w":267,"h":310},
	"178":{"x":536,"y":0,"w":264,"h":314},
	"179":{"x":800,"y":0,"w":267,"h":319},
	"180":{"x":1067,"y":0,"w":269,"h":321},
	"181":{"x":1336,"y":0,"w":272,"h":318}

}}