{"mc":{
	"monster10003_2a":{
		"frameRate":15,
		"frames":[
			{"res":"146","x":-75,"y":-166},
			{"res":"147","x":-78,"y":-191},
			{"res":"148","x":-51,"y":-159},
			{"res":"149","x":-55,"y":-117},
			{"res":"150","x":-57,"y":-114},
			{"res":"151","x":-48,"y":-111}

		]
}},
"res":{
	"146":{"x":0,"y":0,"w":110,"h":186},
	"147":{"x":110,"y":0,"w":128,"h":211},
	"148":{"x":238,"y":0,"w":87,"h":179},
	"149":{"x":325,"y":0,"w":200,"h":137},
	"150":{"x":525,"y":0,"w":163,"h":134},
	"151":{"x":688,"y":0,"w":183,"h":131}

}}