{"mc":{
	"monster10048_3r":{
		"frameRate":12,
		"frames":[
			{"res":"158","x":-36,"y":-117},
			{"res":"159","x":-40,"y":-117},
			{"res":"160","x":-51,"y":-118},
			{"res":"161","x":-64,"y":-118},
			{"res":"162","x":-56,"y":-118},
			{"res":"163","x":-44,"y":-117}

		]
}},
"res":{
	"158":{"x":0,"y":0,"w":86,"h":133},
	"159":{"x":86,"y":0,"w":94,"h":133},
	"160":{"x":180,"y":0,"w":119,"h":136},
	"161":{"x":299,"y":0,"w":137,"h":133},
	"162":{"x":436,"y":0,"w":123,"h":137},
	"163":{"x":559,"y":0,"w":97,"h":134}

}}