{"mc":{
	"monster10052_0r":{
		"frameRate":12,
		"frames":[
			{"res":"104","x":-78,"y":-209},
			{"res":"105","x":-81,"y":-211},
			{"res":"106","x":-78,"y":-210},
			{"res":"107","x":-77,"y":-207},
			{"res":"108","x":-74,"y":-209},
			{"res":"109","x":-75,"y":-211}

		]
}},
"res":{
	"104":{"x":0,"y":0,"w":165,"h":229},
	"105":{"x":165,"y":0,"w":161,"h":226},
	"106":{"x":326,"y":0,"w":154,"h":222},
	"107":{"x":480,"y":0,"w":156,"h":228},
	"108":{"x":636,"y":0,"w":156,"h":215},
	"109":{"x":792,"y":0,"w":158,"h":225}

}}