{"mc":{
	"zhanling1010_1s":{
		"frameRate":10,
		"frames":[
			{"res":"000006","x":-207.5,"y":-347.5},
			{"res":"000007","x":-207.5,"y":-348.5},
			{"res":"000008","x":-207.5,"y":-343.5},
			{"res":"000009","x":-207.5,"y":-342.5},
			{"res":"000010","x":-210.5,"y":-343.5},
			{"res":"000011","x":-208.5,"y":-345.5}

		]
}},
"res":{
	"000006":{"x":0,"y":0,"w":352,"h":399},
	"000007":{"x":352,"y":0,"w":352,"h":397},
	"000008":{"x":704,"y":0,"w":351,"h":394},
	"000009":{"x":1055,"y":0,"w":352,"h":387},
	"000010":{"x":1407,"y":0,"w":356,"h":386},
	"000011":{"x":1407,"y":386,"w":357,"h":394}

}}