{"file":"jueweitb.png","frames":{
"guanyin_05_png":{"x":219,"y":46,"w":20,"h":13,"offX":0,"offY":1,"sourceW":20,"sourceH":14},
"guanyin_06_png":{"x":197,"y":94,"w":20,"h":14,"offX":0,"offY":0,"sourceW":20,"sourceH":14},
"guanyin_07_png":{"x":197,"y":78,"w":20,"h":14,"offX":0,"offY":0,"sourceW":20,"sourceH":14},
"guanyin_08_png":{"x":219,"y":90,"w":20,"h":10,"offX":0,"offY":2,"sourceW":20,"sourceH":14},
"guanyin_09_png":{"x":197,"y":62,"w":20,"h":14,"offX":0,"offY":0,"sourceW":20,"sourceH":14},
"guanyin_10_png":{"x":197,"y":46,"w":20,"h":14,"offX":0,"offY":0,"sourceW":20,"sourceH":14},
"guanyindb_png":{"x":178,"y":116,"w":38,"h":74,"offX":0,"offY":0,"sourceW":38,"sourceH":74},
"juewei_0_1_png":{"x":1,"y":126,"w":86,"h":32,"offX":16,"offY":11,"sourceW":121,"sourceH":43},
"juewei_0_2_png":{"x":1,"y":91,"w":87,"h":33,"offX":16,"offY":10,"sourceW":121,"sourceH":43},
"juewei_0_3_png":{"x":108,"y":81,"w":87,"h":33,"offX":16,"offY":10,"sourceW":121,"sourceH":43},
"juewei_0_4_png":{"x":108,"y":46,"w":87,"h":33,"offX":16,"offY":10,"sourceW":121,"sourceH":43},
"juewei_0_5_png":{"x":90,"y":116,"w":86,"h":33,"offX":17,"offY":10,"sourceW":121,"sourceH":43},
"juewei_0_6_png":{"x":1,"y":46,"w":105,"h":43,"offX":16,"offY":0,"sourceW":121,"sourceH":43},
"juewei_0_7_png":{"x":124,"y":1,"w":120,"h":43,"offX":1,"offY":0,"sourceW":121,"sourceH":43},
"juewei_0_12_png":{"x":1,"y":1,"w":121,"h":43,"offX":0,"offY":0,"sourceW":121,"sourceH":43},
"guanyin_01_png":{"x":219,"y":102,"w":20,"h":6,"offX":0,"offY":4,"sourceW":20,"sourceH":14},
"guanyin_02_png":{"x":219,"y":61,"w":20,"h":12,"offX":0,"offY":2,"sourceW":20,"sourceH":14},
"guanyin_03_png":{"x":218,"y":110,"w":20,"h":13,"offX":0,"offY":1,"sourceW":20,"sourceH":14},
"guanyin_04_png":{"x":219,"y":75,"w":17,"h":13,"offX":1,"offY":1,"sourceW":20,"sourceH":14}}}