{"mc":{
	"skill70633":{
		"frameRate":24,
		"frames":[
			{"res":"101","x":-118,"y":-192},
			{"res":"102","x":-117,"y":-194},
			{"res":"103","x":-116,"y":-191},
			{"res":"104","x":-118,"y":-192},
			{"res":"105","x":-117,"y":-194},
			{"res":"106","x":-115,"y":-190}

		]
}},
"res":{
	"101":{"x":0,"y":0,"w":118,"h":119},
	"102":{"x":118,"y":0,"w":121,"h":124},
	"103":{"x":239,"y":0,"w":123,"h":127},
	"104":{"x":362,"y":0,"w":118,"h":119},
	"105":{"x":480,"y":0,"w":117,"h":121},
	"106":{"x":597,"y":0,"w":115,"h":117}

}}