{"mc":{
	"body307_0_4a":{
		"frameRate":15,
		"frames":[
			{"res":"122","x":-35,"y":-108},
			{"res":"123","x":-31,"y":-114},
			{"res":"124","x":-30,"y":-114},
			{"res":"125","x":-38,"y":-98},
			{"res":"126","x":-53,"y":-85},
			{"res":"127","x":-34,"y":-84},
			{"res":"601","x":-40,"y":-104}

		]
}},
"res":{
	"122":{"x":0,"y":0,"w":81,"h":125},
	"123":{"x":81,"y":0,"w":79,"h":131},
	"124":{"x":160,"y":0,"w":73,"h":132},
	"125":{"x":233,"y":0,"w":79,"h":116},
	"126":{"x":312,"y":0,"w":92,"h":103},
	"127":{"x":404,"y":0,"w":70,"h":102},
	"601":{"x":474,"y":0,"w":87,"h":121}

}}