{"mc":{"body914_1_4r":{"frameRate":12,"frames":[{"res":"113","x":-17,"y":-112},{"res":"114","x":-18,"y":-109},{"res":"115","x":-19,"y":-111},{"res":"116","x":-18,"y":-113},{"res":"117","x":-17,"y":-112},{"res":"118","x":-17,"y":-109},{"res":"119","x":-16,"y":-111},{"res":"120","x":-16,"y":-113}]}},"res":{"113":{"x":0,"y":0,"w":38,"h":124},"114":{"x":38,"y":0,"w":40,"h":118},"115":{"x":78,"y":0,"w":40,"h":106},"116":{"x":118,"y":0,"w":40,"h":107},"117":{"x":158,"y":0,"w":41,"h":124},"118":{"x":199,"y":0,"w":41,"h":117},"119":{"x":240,"y":0,"w":39,"h":106},"120":{"x":279,"y":0,"w":38,"h":105}}}