{"mc":{
	"body804_1_2c":{
		"frameRate":15,
		"frames":[
			{"res":"128","x":-39,"y":-99},
			{"res":"129","x":-37,"y":-101},
			{"res":"130","x":-44,"y":-120},
			{"res":"131","x":-45,"y":-120},
			{"res":"132","x":-41,"y":-120},
			{"res":"133","x":-38,"y":-98},
			{"res":"601","x":-30,"y":-95}

		]
}},
"res":{
	"128":{"x":0,"y":0,"w":61,"h":108},
	"129":{"x":61,"y":0,"w":71,"h":110},
	"130":{"x":132,"y":0,"w":75,"h":129},
	"131":{"x":207,"y":0,"w":78,"h":129},
	"132":{"x":285,"y":0,"w":73,"h":129},
	"133":{"x":358,"y":0,"w":81,"h":107},
	"601":{"x":439,"y":0,"w":60,"h":105}

}}