{"mc":{
	"body109_1_0r":{
		"frameRate":12,
		"frames":[
			{"res":"113","x":-24,"y":-105},
			{"res":"114","x":-26,"y":-104},
			{"res":"115","x":-29,"y":-104},
			{"res":"116","x":-30,"y":-105},
			{"res":"117","x":-30,"y":-105},
			{"res":"118","x":-27,"y":-104},
			{"res":"119","x":-26,"y":-104},
			{"res":"120","x":-25,"y":-105}

		]
}},
"res":{
	"113":{"x":0,"y":0,"w":55,"h":112},
	"114":{"x":55,"y":0,"w":54,"h":110},
	"115":{"x":109,"y":0,"w":55,"h":116},
	"116":{"x":164,"y":0,"w":55,"h":118},
	"117":{"x":219,"y":0,"w":54,"h":111},
	"118":{"x":273,"y":0,"w":53,"h":111},
	"119":{"x":326,"y":0,"w":55,"h":116},
	"120":{"x":381,"y":0,"w":57,"h":118}

}}