{"mc":{
	"body803_0_2r":{
		"frameRate":12,
		"frames":[
			{"res":"113","x":-63,"y":-124},
			{"res":"114","x":-65,"y":-125},
			{"res":"115","x":-64,"y":-123},
			{"res":"116","x":-62,"y":-122},
			{"res":"117","x":-60,"y":-124},
			{"res":"118","x":-58,"y":-126},
			{"res":"119","x":-57,"y":-125},
			{"res":"120","x":-59,"y":-123}

		]
}},
"res":{
	"113":{"x":0,"y":0,"w":106,"h":122},
	"114":{"x":106,"y":0,"w":99,"h":121},
	"115":{"x":205,"y":0,"w":93,"h":123},
	"116":{"x":298,"y":0,"w":79,"h":125},
	"117":{"x":377,"y":0,"w":85,"h":127},
	"118":{"x":462,"y":0,"w":89,"h":124},
	"119":{"x":551,"y":0,"w":91,"h":122},
	"120":{"x":642,"y":0,"w":106,"h":121}

}}