{"mc":{"body908_0_3c":{"frameRate":15,"frames":[{"res":"128","x":-49,"y":-109},{"res":"129","x":-53,"y":-110},{"res":"130","x":-36,"y":-108},{"res":"131","x":-40,"y":-114},{"res":"132","x":-38,"y":-116},{"res":"133","x":-33,"y":-107},{"res":"601","x":-39,"y":-103}]}},"res":{"128":{"x":0,"y":0,"w":75,"h":115},"129":{"x":75,"y":0,"w":79,"h":117},"130":{"x":154,"y":0,"w":62,"h":115},"131":{"x":216,"y":0,"w":70,"h":121},"132":{"x":286,"y":0,"w":73,"h":122},"133":{"x":359,"y":0,"w":68,"h":113},"601":{"x":427,"y":0,"w":77,"h":110}}}