{"mc":{"body918_1_3c":{"frameRate":15,"frames":[{"res":"128","x":-24,"y":-105},{"res":"129","x":-24,"y":-107},{"res":"130","x":-24,"y":-118},{"res":"131","x":-24,"y":-118},{"res":"132","x":-24,"y":-118},{"res":"133","x":-24,"y":-102},{"res":"601","x":-31,"y":-100}]}},"res":{"128":{"x":0,"y":0,"w":50,"h":109},"129":{"x":50,"y":0,"w":49,"h":111},"130":{"x":99,"y":0,"w":49,"h":122},"131":{"x":148,"y":0,"w":49,"h":122},"132":{"x":197,"y":0,"w":49,"h":122},"133":{"x":246,"y":0,"w":50,"h":106},"601":{"x":296,"y":0,"w":67,"h":105}}}