{"mc":{"body903_0_3a":{"frameRate":15,"frames":[{"res":"122","x":-49,"y":-107},{"res":"123","x":-46,"y":-109},{"res":"124","x":-46,"y":-106},{"res":"125","x":-48,"y":-100},{"res":"126","x":-47,"y":-100},{"res":"127","x":-46,"y":-100},{"res":"601","x":-47,"y":-105}]}},"res":{"122":{"x":0,"y":0,"w":89,"h":112},"123":{"x":89,"y":0,"w":88,"h":115},"124":{"x":177,"y":0,"w":91,"h":118},"125":{"x":268,"y":0,"w":90,"h":115},"126":{"x":358,"y":0,"w":89,"h":113},"127":{"x":447,"y":0,"w":88,"h":104},"601":{"x":535,"y":0,"w":87,"h":110}}}