{"mc":{
	"body802_0_2r":{
		"frameRate":12,
		"frames":[
			{"res":"113","x":-45,"y":-106},
			{"res":"114","x":-53,"y":-107},
			{"res":"115","x":-56,"y":-105},
			{"res":"116","x":-36,"y":-103},
			{"res":"117","x":-45,"y":-106},
			{"res":"118","x":-55,"y":-107},
			{"res":"119","x":-51,"y":-107},
			{"res":"120","x":-39,"y":-104}

		]
}},
"res":{
	"113":{"x":0,"y":0,"w":83,"h":104},
	"114":{"x":83,"y":0,"w":87,"h":104},
	"115":{"x":170,"y":0,"w":84,"h":106},
	"116":{"x":254,"y":0,"w":55,"h":107},
	"117":{"x":309,"y":0,"w":70,"h":108},
	"118":{"x":379,"y":0,"w":85,"h":101},
	"119":{"x":464,"y":0,"w":88,"h":104},
	"120":{"x":552,"y":0,"w":84,"h":103}

}}