{"mc":{
	"body801_0_1a":{
		"frameRate":15,
		"frames":[
			{"res":"122","x":-59,"y":-123},
			{"res":"123","x":-73,"y":-129},
			{"res":"124","x":-59,"y":-137},
			{"res":"125","x":-62,"y":-137},
			{"res":"126","x":-55,"y":-136},
			{"res":"127","x":-54,"y":-136},
			{"res":"601","x":-60,"y":-131}

		]
}},
"res":{
	"122":{"x":0,"y":0,"w":112,"h":175},
	"123":{"x":112,"y":0,"w":123,"h":180},
	"124":{"x":235,"y":0,"w":117,"h":187},
	"125":{"x":352,"y":0,"w":146,"h":186},
	"126":{"x":498,"y":0,"w":138,"h":184},
	"127":{"x":636,"y":0,"w":131,"h":184},
	"601":{"x":767,"y":0,"w":116,"h":182}

}}