{"file":"tujian.png","frames":{
"biaoti_tujian":{"x":91,"y":184,"w":80,"h":25,"offX":12,"offY":5,"sourceW":103,"sourceH":34},
"tujian_1a":{"x":46,"y":126,"w":43,"h":59,"offX":0,"offY":0,"sourceW":43,"sourceH":59},
"tujian_1b":{"x":203,"y":216,"w":7,"h":3,"offX":0,"offY":0,"sourceW":7,"sourceH":3},
"tujian_1c":{"x":1,"y":226,"w":182,"h":3,"offX":0,"offY":0,"sourceW":182,"sourceH":3},
"tujian_2a":{"x":1,"y":126,"w":43,"h":59,"offX":0,"offY":0,"sourceW":43,"sourceH":59},
"tujian_2b":{"x":204,"y":189,"w":7,"h":3,"offX":0,"offY":0,"sourceW":7,"sourceH":3},
"tujian_2c":{"x":1,"y":216,"w":182,"h":3,"offX":0,"offY":0,"sourceW":182,"sourceH":3},
"tujian_3a":{"x":189,"y":123,"w":43,"h":59,"offX":0,"offY":0,"sourceW":43,"sourceH":59},
"tujian_3b":{"x":185,"y":216,"w":7,"h":3,"offX":0,"offY":0,"sourceW":7,"sourceH":3},
"tujian_3c":{"x":1,"y":231,"w":182,"h":3,"offX":0,"offY":0,"sourceW":182,"sourceH":3},
"tujian_4a":{"x":189,"y":62,"w":43,"h":59,"offX":0,"offY":0,"sourceW":43,"sourceH":59},
"tujian_4b":{"x":204,"y":184,"w":7,"h":3,"offX":0,"offY":0,"sourceW":7,"sourceH":3},
"tujian_4c":{"x":1,"y":236,"w":182,"h":3,"offX":0,"offY":0,"sourceW":182,"sourceH":3},
"tujian_5a":{"x":189,"y":1,"w":43,"h":59,"offX":0,"offY":0,"sourceW":43,"sourceH":59},
"tujian_5b":{"x":194,"y":216,"w":7,"h":3,"offX":0,"offY":0,"sourceW":7,"sourceH":3},
"tujian_5c":{"x":1,"y":221,"w":182,"h":3,"offX":0,"offY":0,"sourceW":182,"sourceH":3},
"tujianexp":{"x":173,"y":184,"w":29,"h":30,"offX":0,"offY":0,"sourceW":29,"sourceH":30},
"tujiankabg":{"x":1,"y":1,"w":186,"h":123,"offX":0,"offY":0,"sourceW":186,"sourceH":123}}}