{"mc":{"weapon905_1_0r":{"frameRate":12,"frames":[{"res":"101","x":-40,"y":-188},{"res":"102","x":-39,"y":-224},{"res":"103","x":-46,"y":-251},{"res":"104","x":-47,"y":-280},{"res":"105","x":-43,"y":-279},{"res":"106","x":-42,"y":-271},{"res":"107","x":-39,"y":-226},{"res":"108","x":-33,"y":-178}]}},"res":{"101":{"x":0,"y":0,"w":104,"h":186},"102":{"x":104,"y":0,"w":100,"h":227},"103":{"x":204,"y":0,"w":102,"h":250},"104":{"x":306,"y":0,"w":104,"h":264},"105":{"x":410,"y":0,"w":103,"h":267},"106":{"x":513,"y":0,"w":103,"h":269},"107":{"x":616,"y":0,"w":103,"h":226},"108":{"x":719,"y":0,"w":101,"h":175}}}