{"mc":{
	"weapon113_1_4r":{
		"frameRate":12,
		"frames":[
			{"res":"113","x":-31,"y":-91},
			{"res":"114","x":-19,"y":-85},
			{"res":"115","x":-19,"y":-124},
			{"res":"116","x":-15,"y":-156},
			{"res":"117","x":-15,"y":-151},
			{"res":"118","x":-18,"y":-121},
			{"res":"119","x":-22,"y":-86},
			{"res":"120","x":-27,"y":-92}

		]
}},
"res":{
	"113":{"x":0,"y":0,"w":26,"h":105},
	"114":{"x":26,"y":0,"w":13,"h":74},
	"115":{"x":39,"y":0,"w":21,"h":99},
	"116":{"x":60,"y":0,"w":19,"h":140},
	"117":{"x":79,"y":0,"w":18,"h":134},
	"118":{"x":97,"y":0,"w":18,"h":94},
	"119":{"x":115,"y":0,"w":15,"h":74},
	"120":{"x":130,"y":0,"w":22,"h":102}

}}