{"mc":{"weaponsoul101_2_0r":{"frameRate":12,"frames":[{"res":"113","x":-13,"y":-128},{"res":"114","x":-7,"y":-92},{"res":"115","x":2,"y":-70},{"res":"116","x":-38,"y":-165},{"res":"117","x":-49,"y":-209},{"res":"118","x":-52,"y":-224},{"res":"119","x":-45,"y":-210},{"res":"120","x":-34,"y":-159}]}},"res":{"113":{"x":0,"y":0,"w":84,"h":111},"114":{"x":84,"y":0,"w":75,"h":82},"115":{"x":159,"y":0,"w":38,"h":39},"116":{"x":197,"y":0,"w":78,"h":138},"117":{"x":275,"y":0,"w":95,"h":169},"118":{"x":370,"y":0,"w":91,"h":172},"119":{"x":461,"y":0,"w":87,"h":178},"120":{"x":548,"y":0,"w":76,"h":136}}}