{"mc":{
	"weapon901_1_4c":{
		"frameRate":15,
		"frames":[
			{"res":"128","x":-32,"y":-119},
			{"res":"129","x":-21,"y":-214},
			{"res":"130","x":-8,"y":-257},
			{"res":"131","x":-8,"y":-257},
			{"res":"132","x":-8,"y":-257},
			{"res":"133","x":-12,"y":-66},
			{"res":"601","x":-80,"y":-225}

		]
}},
"res":{
	"128":{"x":0,"y":0,"w":83,"h":78},
	"129":{"x":83,"y":0,"w":68,"h":160},
	"130":{"x":151,"y":0,"w":26,"h":179},
	"131":{"x":177,"y":0,"w":26,"h":179},
	"132":{"x":203,"y":0,"w":26,"h":179},
	"133":{"x":229,"y":0,"w":11,"h":109},
	"601":{"x":240,"y":0,"w":55,"h":190}

}}