{"mc":{
	"weapon112_1_1c":{
		"frameRate":15,
		"frames":[
			{"res":"128","x":-7,"y":-224},
			{"res":"129","x":-33,"y":-247},
			{"res":"130","x":-34,"y":-248},
			{"res":"131","x":-34,"y":-248},
			{"res":"132","x":-34,"y":-248},
			{"res":"133","x":-1,"y":-148},
			{"res":"601","x":-14,"y":-142}

		]
}},
"res":{
	"128":{"x":0,"y":0,"w":63,"h":205},
	"129":{"x":63,"y":0,"w":86,"h":184},
	"130":{"x":149,"y":0,"w":69,"h":166},
	"131":{"x":218,"y":0,"w":69,"h":166},
	"132":{"x":287,"y":0,"w":69,"h":166},
	"133":{"x":356,"y":0,"w":147,"h":96},
	"601":{"x":503,"y":0,"w":79,"h":105}

}}