{"mc":{"weaponsoul101_2_4a":{"frameRate":15,"frames":[{"res":"122","x":-119,"y":-205},{"res":"123","x":-54,"y":-192},{"res":"124","x":-56,"y":-183},{"res":"125","x":-89,"y":-206},{"res":"126","x":-28,"y":-32},{"res":"127","x":-57,"y":-62},{"res":"601","x":-117,"y":-231}]}},"res":{"122":{"x":0,"y":0,"w":124,"h":177},"123":{"x":124,"y":0,"w":178,"h":121},"124":{"x":302,"y":0,"w":126,"h":107},"125":{"x":428,"y":0,"w":89,"h":162},"126":{"x":517,"y":0,"w":96,"h":136},"127":{"x":613,"y":0,"w":126,"h":142},"601":{"x":739,"y":0,"w":117,"h":214}}}