{"mc":{"weaponsoul302_2_0a":{"frameRate":15,"frames":[{"res":"122","x":-21,"y":-141},{"res":"123","x":-75,"y":-111},{"res":"124","x":-21,"y":-126},{"res":"125","x":-21,"y":-176},{"res":"126","x":-47,"y":-125},{"res":"127","x":-12,"y":-111},{"res":"601","x":0,"y":-119}]}},"res":{"122":{"x":0,"y":0,"w":108,"h":103},"123":{"x":108,"y":0,"w":130,"h":118},"124":{"x":238,"y":0,"w":65,"h":92},"125":{"x":303,"y":0,"w":96,"h":106},"126":{"x":399,"y":0,"w":90,"h":104},"127":{"x":489,"y":0,"w":46,"h":104},"601":{"x":535,"y":0,"w":83,"h":74}}}