{"mc":{
	"weapon310_0_3r":{
		"frameRate":12,
		"frames":[
			{"res":"113","x":-37,"y":-80},
			{"res":"114","x":-41,"y":-74},
			{"res":"115","x":-39,"y":-69},
			{"res":"116","x":-20,"y":-84},
			{"res":"117","x":-10,"y":-104},
			{"res":"118","x":-11,"y":-116},
			{"res":"119","x":-13,"y":-103},
			{"res":"120","x":-32,"y":-89}

		]
}},
"res":{
	"113":{"x":0,"y":0,"w":60,"h":79},
	"114":{"x":60,"y":0,"w":57,"h":75},
	"115":{"x":117,"y":0,"w":69,"h":74},
	"116":{"x":186,"y":0,"w":79,"h":84},
	"117":{"x":265,"y":0,"w":70,"h":77},
	"118":{"x":335,"y":0,"w":71,"h":78},
	"119":{"x":406,"y":0,"w":63,"h":74},
	"120":{"x":469,"y":0,"w":71,"h":83}

}}