{"mc":{
	"weapon106_1_1c":{
		"frameRate":15,
		"frames":[
			{"res":"128","x":10,"y":-194},
			{"res":"129","x":-7,"y":-230},
			{"res":"130","x":-14,"y":-235},
			{"res":"131","x":-14,"y":-235},
			{"res":"132","x":-14,"y":-235},
			{"res":"133","x":14,"y":-118},
			{"res":"601","x":8,"y":-133}

		]
}},
"res":{
	"128":{"x":0,"y":0,"w":40,"h":154},
	"129":{"x":40,"y":0,"w":49,"h":147},
	"130":{"x":89,"y":0,"w":38,"h":135},
	"131":{"x":127,"y":0,"w":38,"h":135},
	"132":{"x":165,"y":0,"w":38,"h":135},
	"133":{"x":203,"y":0,"w":111,"h":56},
	"601":{"x":314,"y":0,"w":42,"h":84}

}}