{"mc":{
	"weapon210_0_0a":{
		"frameRate":15,
		"frames":[
			{"res":"122","x":1,"y":-152},
			{"res":"123","x":-80,"y":-87},
			{"res":"124","x":-30,"y":-145},
			{"res":"125","x":-7,"y":-183},
			{"res":"126","x":-42,"y":-99},
			{"res":"127","x":-35,"y":-97},
			{"res":"601","x":15,"y":-131}

		]
}},
"res":{
	"122":{"x":0,"y":0,"w":67,"h":153},
	"123":{"x":67,"y":0,"w":159,"h":73},
	"124":{"x":226,"y":0,"w":91,"h":107},
	"125":{"x":317,"y":0,"w":69,"h":103},
	"126":{"x":386,"y":0,"w":82,"h":68},
	"127":{"x":468,"y":0,"w":90,"h":68},
	"601":{"x":558,"y":0,"w":62,"h":94}

}}