{"mc":{"weapon908_0_1r":{"frameRate":12,"frames":[{"res":"113","x":-20,"y":-85},{"res":"114","x":-22,"y":-61},{"res":"115","x":-13,"y":-60},{"res":"116","x":4,"y":-140},{"res":"117","x":15,"y":-191},{"res":"118","x":17,"y":-207},{"res":"119","x":12,"y":-189},{"res":"120","x":-11,"y":-130}]}},"res":{"113":{"x":0,"y":0,"w":130,"h":56},"114":{"x":130,"y":0,"w":120,"h":35},"115":{"x":250,"y":0,"w":108,"h":32},"116":{"x":358,"y":0,"w":87,"h":111},"117":{"x":445,"y":0,"w":45,"h":156},"118":{"x":490,"y":0,"w":17,"h":165},"119":{"x":507,"y":0,"w":44,"h":159},"120":{"x":551,"y":0,"w":103,"h":107}}}