{"mc":{"weapon905_0_4c":{"frameRate":15,"frames":[{"res":"101","x":-111,"y":-192},{"res":"102","x":-45,"y":-232},{"res":"103","x":-52,"y":-253},{"res":"104","x":-60,"y":-289},{"res":"105","x":-63,"y":-296},{"res":"106","x":-64,"y":-91},{"res":"107","x":-124,"y":-256}]}},"res":{"101":{"x":0,"y":0,"w":133,"h":187},"102":{"x":133,"y":0,"w":121,"h":216},"103":{"x":254,"y":0,"w":173,"h":224},"104":{"x":427,"y":0,"w":153,"h":242},"105":{"x":580,"y":0,"w":126,"h":251},"106":{"x":706,"y":0,"w":103,"h":134},"107":{"x":809,"y":0,"w":133,"h":254}}}