{"mc":{
	"weapon111_1_2a":{
		"frameRate":15,
		"frames":[
			{"res":"122","x":-28,"y":-161},
			{"res":"123","x":-114,"y":-167},
			{"res":"124","x":-123,"y":-133},
			{"res":"125","x":-5,"y":-173},
			{"res":"126","x":13,"y":-58},
			{"res":"127","x":-21,"y":-63},
			{"res":"601","x":-66,"y":-148}

		]
}},
"res":{
	"122":{"x":0,"y":0,"w":58,"h":142},
	"123":{"x":58,"y":0,"w":93,"h":109},
	"124":{"x":151,"y":0,"w":166,"h":61},
	"125":{"x":317,"y":0,"w":85,"h":121},
	"126":{"x":402,"y":0,"w":168,"h":53},
	"127":{"x":570,"y":0,"w":187,"h":69},
	"601":{"x":757,"y":0,"w":102,"h":126}

}}