{"mc":{
	"weapon106_0_0a":{
		"frameRate":15,
		"frames":[
			{"res":"122","x":21,"y":-172},
			{"res":"123","x":-101,"y":-77},
			{"res":"124","x":-43,"y":-121},
			{"res":"125","x":15,"y":-184},
			{"res":"126","x":-53,"y":-80},
			{"res":"127","x":-47,"y":-80},
			{"res":"601","x":27,"y":-133}

		]
}},
"res":{
	"122":{"x":0,"y":0,"w":65,"h":123},
	"123":{"x":65,"y":0,"w":128,"h":51},
	"124":{"x":193,"y":0,"w":75,"h":96},
	"125":{"x":268,"y":0,"w":55,"h":79},
	"126":{"x":323,"y":0,"w":49,"h":38},
	"127":{"x":372,"y":0,"w":73,"h":44},
	"601":{"x":445,"y":0,"w":57,"h":75}

}}