{"mc":{"weapon907_0_2r":{"frameRate":12,"frames":[{"res":"113","x":-60,"y":-143},{"res":"114","x":-77,"y":-123},{"res":"115","x":-67,"y":-136},{"res":"116","x":-34,"y":-140},{"res":"117","x":-31,"y":-185},{"res":"118","x":-50,"y":-205},{"res":"119","x":-41,"y":-180},{"res":"120","x":-49,"y":-138}]}},"res":{"113":{"x":0,"y":0,"w":213,"h":176},"114":{"x":213,"y":0,"w":202,"h":170},"115":{"x":415,"y":0,"w":202,"h":166},"116":{"x":617,"y":0,"w":193,"h":165},"117":{"x":810,"y":0,"w":169,"h":192},"118":{"x":979,"y":0,"w":154,"h":202},"119":{"x":1133,"y":0,"w":165,"h":195},"120":{"x":1298,"y":0,"w":195,"h":158}}}