{"mc":{
	"weapon301_1_2a":{
		"frameRate":15,
		"frames":[
			{"res":"122","x":-7,"y":-116},
			{"res":"123","x":-89,"y":-136},
			{"res":"124","x":-80,"y":-112},
			{"res":"125","x":26,"y":-143},
			{"res":"126","x":27,"y":-46},
			{"res":"127","x":7,"y":-46},
			{"res":"601","x":-28,"y":-111}

		]
}},
"res":{
	"122":{"x":0,"y":0,"w":19,"h":76},
	"123":{"x":19,"y":0,"w":56,"h":66},
	"124":{"x":75,"y":0,"w":99,"h":23},
	"125":{"x":174,"y":0,"w":30,"h":75},
	"126":{"x":204,"y":0,"w":99,"h":23},
	"127":{"x":303,"y":0,"w":105,"h":28},
	"601":{"x":408,"y":0,"w":48,"h":70}

}}