{"mc":{
	"weapon212_0_0a":{
		"frameRate":15,
		"frames":[
			{"res":"122","x":3,"y":-178},
			{"res":"123","x":-105,"y":-86},
			{"res":"124","x":-45,"y":-143},
			{"res":"125","x":-5,"y":-192},
			{"res":"126","x":-56,"y":-98},
			{"res":"127","x":-49,"y":-95},
			{"res":"601","x":15,"y":-142}

		]
}},
"res":{
	"122":{"x":0,"y":0,"w":77,"h":175},
	"123":{"x":77,"y":0,"w":179,"h":74},
	"124":{"x":256,"y":0,"w":103,"h":128},
	"125":{"x":359,"y":0,"w":79,"h":110},
	"126":{"x":438,"y":0,"w":94,"h":66},
	"127":{"x":532,"y":0,"w":102,"h":76},
	"601":{"x":634,"y":0,"w":70,"h":107}

}}