{"mc":{"weapon911_1_4r":{"frameRate":12,"frames":[{"res":"113","x":-73,"y":-82},{"res":"114","x":-41,"y":-86},{"res":"115","x":-57,"y":-143},{"res":"116","x":-47,"y":-182},{"res":"117","x":-52,"y":-177},{"res":"118","x":-55,"y":-145},{"res":"119","x":-63,"y":-104},{"res":"120","x":-68,"y":-91}]}},"res":{"113":{"x":0,"y":0,"w":100,"h":122},"114":{"x":100,"y":0,"w":66,"h":66},"115":{"x":166,"y":0,"w":100,"h":125},"116":{"x":266,"y":0,"w":90,"h":137},"117":{"x":356,"y":0,"w":101,"h":133},"118":{"x":457,"y":0,"w":101,"h":122},"119":{"x":558,"y":0,"w":98,"h":116},"120":{"x":656,"y":0,"w":98,"h":118}}}