{"mc":{
	"weapon805_0_2c":{
		"frameRate":15,
		"frames":[
			{"res":"128","x":9,"y":-119},
			{"res":"129","x":13,"y":-192},
			{"res":"130","x":-16,"y":-203},
			{"res":"131","x":-76,"y":-192},
			{"res":"132","x":-9,"y":-214},
			{"res":"133","x":21,"y":-87},
			{"res":"601","x":-55,"y":-115}

		]
}},
"res":{
	"128":{"x":0,"y":0,"w":48,"h":81},
	"129":{"x":48,"y":0,"w":31,"h":123},
	"130":{"x":79,"y":0,"w":48,"h":125},
	"131":{"x":127,"y":0,"w":91,"h":100},
	"132":{"x":218,"y":0,"w":33,"h":129},
	"133":{"x":251,"y":0,"w":129,"h":36},
	"601":{"x":380,"y":0,"w":75,"h":78}

}}