{"mc":{
	"weapon115_0_0a":{
		"frameRate":15,
		"frames":[
			{"res":"122","x":13,"y":-196},
			{"res":"123","x":-126,"y":-90},
			{"res":"124","x":-57,"y":-131},
			{"res":"125","x":7,"y":-202},
			{"res":"126","x":-66,"y":-100},
			{"res":"127","x":-61,"y":-100},
			{"res":"601","x":20,"y":-149}

		]
}},
"res":{
	"122":{"x":0,"y":0,"w":88,"h":164},
	"123":{"x":88,"y":0,"w":174,"h":85},
	"124":{"x":262,"y":0,"w":100,"h":128},
	"125":{"x":362,"y":0,"w":74,"h":107},
	"126":{"x":436,"y":0,"w":90,"h":82},
	"127":{"x":526,"y":0,"w":98,"h":87},
	"601":{"x":624,"y":0,"w":78,"h":102}

}}