{"mc":{"weapon915_1_1r":{"frameRate":12,"frames":[{"res":"113","x":-70,"y":-188},{"res":"114","x":-53,"y":-238},{"res":"115","x":-39,"y":-255},{"res":"116","x":-33,"y":-274},{"res":"117","x":-34,"y":-316},{"res":"118","x":-45,"y":-255},{"res":"119","x":-61,"y":-247},{"res":"120","x":-70,"y":-182}]}},"res":{"113":{"x":0,"y":0,"w":255,"h":198},"114":{"x":255,"y":0,"w":230,"h":253},"115":{"x":485,"y":0,"w":187,"h":271},"116":{"x":672,"y":0,"w":155,"h":281},"117":{"x":827,"y":0,"w":159,"h":327},"118":{"x":986,"y":0,"w":191,"h":273},"119":{"x":1177,"y":0,"w":256,"h":265},"120":{"x":1433,"y":0,"w":252,"h":190}}}